{
	"info": {
		"_postman_id": "f1484a71-7e80-4a3a-9b29-da4d025fff00",
		"name": "Homework3/4",
		"schema": "https://schema.getpostman.com/json/collection/v2.1.0/collection.json",
		"_exporter_id": "33565482"
	},
	"item": [
		{
			"name": "GetAllTasks",
			"request": {
				"method": "GET",
				"header": []
			},
			"response": []
		},
		{
			"name": "Get task by id",
			"request": {
				"method": "GET",
				"header": [],
				"url": {
					"raw": "http://localhost:4000/api/tasks/:id",
					"protocol": "http",
					"host": [
						"localhost"
					],
					"port": "4000",
					"path": [
						"api",
						"tasks",
						":id"
					],
					"variable": [
						{
							"key": "id",
							"value": "\"8a41be63-42c7-4c63-a683-a8a83c59077e\""
						}
					]
				}
			},
			"response": []
		},
		{
			"name": "Create task",
			"request": {
				"method": "POST",
				"header": [],
				"body": {
					"mode": "raw",
					"raw": "{\r\n    \r\n    \"text\": \"Watch movie\",\r\n    \"author\": \"Nikola Bozaroski\"\r\n    }",
					"options": {
						"raw": {
							"language": "json"
						}
					}
				},
				"url": {
					"raw": "http://localhost:4000/api/tasks",
					"protocol": "http",
					"host": [
						"localhost"
					],
					"port": "4000",
					"path": [
						"api",
						"tasks"
					]
				}
			},
			"response": []
		},
		{
			"name": "Update task",
			"request": {
				"method": "POST",
				"header": [],
				"url": {
					"raw": "http://localhost:4000/api/tasks/:id/",
					"protocol": "http",
					"host": [
						"localhost"
					],
					"port": "4000",
					"path": [
						"api",
						"tasks",
						":id",
						""
					],
					"variable": [
						{
							"key": "id",
							"value": ""
						}
					]
				}
			},
			"response": []
		},
		{
			"name": "Delete task",
			"request": {
				"method": "DELETE",
				"header": [],
				"url": {
					"raw": "http://localhost:4000/api/tasks/:id/",
					"protocol": "http",
					"host": [
						"localhost"
					],
					"port": "4000",
					"path": [
						"api",
						"tasks",
						":id",
						""
					],
					"variable": [
						{
							"key": "id",
							"value": ""
						}
					]
				}
			},
			"response": []
		},
		{
			"name": "Delete all tasks",
			"request": {
				"method": "DELETE",
				"header": [],
				"url": {
					"raw": "http://localhost:4000/api/tasks/:id/",
					"protocol": "http",
					"host": [
						"localhost"
					],
					"port": "4000",
					"path": [
						"api",
						"tasks",
						":id",
						""
					],
					"variable": [
						{
							"key": "id",
							"value": ""
						}
					]
				}
			},
			"response": []
		}
	]
}